[
  {
    "DateFin": "2024-04-04",
    "HeureFin": "17:30",
    "Matiere": "Reservation de salles",
    "Salle": "amphi ada",
    "Summary": "Reservation de salles",
    "Enseignant": "Noe Cecillon",
    "DateDebut": "2024-04-04",
    "HeureDebut": "16:00"
  },
  {
    "DateFin": "2024-04-02",
    "HeureFin": "10:00",
    "Matiere": "Reservation de salles",
    "Salle": "amphi ada",
    "Summary": "Reservation de salles",
    "Enseignant": "Noe Cecillon",
    "DateDebut": "2024-04-02",
    "HeureDebut": "08:30"
  },
  {
    "DateFin": "2024-04-12",
    "HeureFin": "15:00",
    "Matiere": "Reservation de salles",
    "Salle": "amphi ada",
    "Summary": "Reservation de salles",
    "Enseignant": "Noe Cecillon",
    "DateDebut": "2024-04-12",
    "HeureDebut": "13:00"
  },
  {
    "DateFin": "2024-04-03",
    "HeureFin": "11:30",
    "Matiere": "Reservation de salles",
    "Salle": "amphi ada",
    "Summary": "Reservation de salles",
    "Enseignant": "Noe Cecillon",
    "DateDebut": "2024-04-03",
    "HeureDebut": "08:30"
  },
  {
    "DateFin": "2024-04-05",
    "HeureFin": "18:00",
    "Matiere": "Reservation de salles",
    "Salle": "amphi ada",
    "Summary": "Reservation de salles",
    "Enseignant": "Noe Cecillon",
    "DateDebut": "2024-04-05",
    "HeureDebut": "17:00"
  }
]